RecipeScraper.py
boba_recipescraper-0.0.1.dist-info/licenses/LICENSE.txt
boba_recipescraper-0.0.1.dist-info/METADATA
boba_recipescraper-0.0.1.dist-info/WHEEL
boba_recipescraper-0.0.1.dist-info/top_level.txt
boba_recipescraper-0.0.1.dist-info/RECORD
